api4bing/__init__.py
api4bing/__main__.py
api4bing/cross_open.py
api4bing/headers.py
api4bing-0.1.4.dist-info/METADATA
api4bing-0.1.4.dist-info/WHEEL
api4bing-0.1.4.dist-info/RECORD
