Metadata-Version: 2.1
Name: api4bing
Version: 0.1.4
Summary: Add your description here
Author-email: thewh1teagle <61390950+thewh1teagle@users.noreply.github.com>
Requires-Python: >=3.8
Requires-Dist: bs4>=0.0.1
Requires-Dist: requests>=2.31.0
Requires-Dist: rookiepy>=0.2.7
